ghosttag/__init__.py
ghosttag/_version.py
ghosttag/ghosttag.py
ghosttag-0.0.1.dist-info/DESCRIPTION.rst
ghosttag-0.0.1.dist-info/entry_points.txt
ghosttag-0.0.1.dist-info/METADATA
ghosttag-0.0.1.dist-info/metadata.json
ghosttag-0.0.1.dist-info/RECORD
ghosttag-0.0.1.dist-info/top_level.txt
ghosttag-0.0.1.dist-info/WHEEL
