Metadata-Version: 2.0
Name: ghosttag
Version: 0.0.1
Summary: Tag updater for Ghost
Home-page: https://github.com/devanp92/ghost-tag
Author: Devan Patel
Author-email: devanppatel92@gmail.com
License: MIT
Platform: UNKNOWN
Requires-Dist: docopt (==0.6.1)
Requires-Dist: tabulate (==0.7.5)
